{
    "logs": [
        {
            "outputFile": "com.sallie.app-mergeDebugResources-29:/values-v16/values-v16.xml",
            "map": [
                {
                    "source": "C:\\Users\\chell\\.gradle\\caches\\8.13\\transforms\\67db5c9d7c8a7803a8b2f5d54478aaad\\transformed\\appcompat-1.6.1\\res\\values-v16\\values-v16.xml",
                    "from": {
                        "startLines": "2",
                        "startColumns": "4",
                        "startOffsets": "55",
                        "endLines": "5",
                        "endColumns": "12",
                        "endOffsets": "223"
                    },
                    "to": {
                        "startLines": "3",
                        "startColumns": "4",
                        "startOffsets": "121",
                        "endLines": "6",
                        "endColumns": "12",
                        "endOffsets": "289"
                    }
                },
                {
                    "source": "C:\\Users\\chell\\.gradle\\caches\\8.13\\transforms\\4500d51c5704246dcb082ab08c1197f1\\transformed\\core-1.12.0\\res\\values-v16\\values-v16.xml",
                    "from": {
                        "startLines": "2",
                        "startColumns": "4",
                        "startOffsets": "55",
                        "endColumns": "65",
                        "endOffsets": "116"
                    }
                }
            ]
        }
    ]
}

{
    "logs": [
        {
            "outputFile": "com.sallie.app-mergeDebugResources-60:/values-v16/values-v16.xml",
            "map": [
                {
                    "source": "C:\\Users\\chell\\.gradle\\caches\\9.0.0\\transforms\\d983d8111b4d7507de44f92b4d35b638\\transformed\\appcompat-1.7.0\\res\\values-v16\\values-v16.xml",
                    "from": {
                        "startLines": "2",
                        "startColumns": "4",
                        "startOffsets": "55",
                        "endLines": "5",
                        "endColumns": "12",
                        "endOffsets": "223"
                    }
                }
            ]
        }
    ]
}